gitsql/__init__.py
gitsql/cli.py
gitsql/openmldb_importer.py
gitsql-0.1.1.1.dist-info/LICENSE
gitsql-0.1.1.1.dist-info/METADATA
gitsql-0.1.1.1.dist-info/WHEEL
gitsql-0.1.1.1.dist-info/entry_points.txt
gitsql-0.1.1.1.dist-info/top_level.txt
gitsql-0.1.1.1.dist-info/RECORD
