Metadata-Version: 2.1
Name: gitsql
Version: 0.1.1.1
Summary: Query Git with SQL
Home-page: https://github.com/tobegit3hub/gitsql
Author: tobe
Author-email: tobeg3oogle@gmail.com
License: UNKNOWN
Platform: UNKNOWN
Classifier: Programming Language :: Python :: 3
License-File: LICENSE
Requires-Dist: GitPython
Requires-Dist: openmldb (>=0.4.2)
Requires-Dist: openmldb-lab
